lightning_nc/__init__.py
lightning_nc/finetuning.py
lightning_nc/pruning.py
lightning_nc/quantization.py
lightning_nc-0.0.3.dist-info/LICENSE.md
lightning_nc-0.0.3.dist-info/METADATA
lightning_nc-0.0.3.dist-info/WHEEL
lightning_nc-0.0.3.dist-info/RECORD
