Metadata-Version: 2.1
Name: lightning-nc
Version: 0.0.3
Summary: 
Author: Clément POIRET
Author-email: poiret.clement@outlook.fr
Requires-Python: >=3.8.0
Classifier: Programming Language :: Python :: 3
Classifier: Programming Language :: Python :: 3.8
Classifier: Programming Language :: Python :: 3.9
Classifier: Programming Language :: Python :: 3.10
Classifier: Programming Language :: Python :: 3.11
Classifier: Programming Language :: Python :: 3.12
Requires-Dist: lightning (>=2.0.0)
Requires-Dist: neural-compressor (>=2.0.0)
